orbdtools/__init__.py
orbdtools/arcassocia/__init__.py
orbdtools/arcmatch/__init__.py
orbdtools/arcmatch/optical.py
orbdtools/arcmatch/parse_tle.py
orbdtools/arcmatch/radar.py
orbdtools/classes/__init__.py
orbdtools/classes/class_arcobs.py
orbdtools/classes/class_bodies.py
orbdtools/classes/class_cod.py
orbdtools/classes/class_frametrans.py
orbdtools/classes/class_iod.py
orbdtools/classes/class_keprvtrans.py
orbdtools/classes/class_orbeletrans.py
orbdtools/classes/class_tle.py
orbdtools/cod/__init__.py
orbdtools/cod/sgp4/__init__.py
orbdtools/cod/sgp4/sgp4_bstar.py
orbdtools/cod/sgp4/sgp4_init.py
orbdtools/cod/sgp4/sgp4_od/__init__.py
orbdtools/cod/sgp4/sgp4_od/optical.py
orbdtools/cod/sgp4/sgp4_od/radar.py
orbdtools/iod/__init__.py
orbdtools/iod/common.py
orbdtools/iod/angular/__init__.py
orbdtools/iod/angular/circular.py
orbdtools/iod/angular/doubleR.py
orbdtools/iod/angular/fg_series.py
orbdtools/iod/angular/gauss.py
orbdtools/iod/angular/gooding.py
orbdtools/iod/angular/karimi.py
orbdtools/iod/angular/laplace.py
orbdtools/iod/angular/multilaplace.py
orbdtools/iod/angular/ref_vec.py
orbdtools/iod/lambert/__init__.py
orbdtools/iod/lambert/battin.py
orbdtools/iod/lambert/izzo.py
orbdtools/iod/lambert/universal.py
orbdtools/iod/radar/__init__.py
orbdtools/iod/radar/fg_series.py
orbdtools/iod/radar/gibbs.py
orbdtools/iod/radar/multifitting.py
orbdtools/pod/__init__.py
orbdtools/transform/__init__.py
orbdtools/transform/frame_trans.py
orbdtools/transform/kep_rv_trans.py
orbdtools/transform/orbele_trans.py
orbdtools/utils/Const.py
orbdtools/utils/__init__.py
orbdtools/utils/data_download.py
orbdtools/utils/data_prepare.py
orbdtools/utils/math.py
orbdtools/utils/preprocessing.py
orbdtools/utils/try_download.py
orbdtools-0.2.1.dist-info/LICENSE
orbdtools-0.2.1.dist-info/METADATA
orbdtools-0.2.1.dist-info/WHEEL
orbdtools-0.2.1.dist-info/top_level.txt
orbdtools-0.2.1.dist-info/RECORD
