Metadata-Version: 2.1
Name: orbdtools
Version: 0.2.1
Summary: A set of routines for data processing related to ORBit Determination(ORBD) of space objects
Home-page: https://github.com/lcx366/ORBDTOOLS
Author: Chunxiao Li
Author-email: lcx366@126.com
License: MIT
Keywords: Arc Matching,Arc Association,Initial OD,Cataloging OD,Precise OD
Classifier: Development Status :: 4 - Beta
Classifier: Intended Audience :: Education
Classifier: Intended Audience :: Science/Research
Classifier: Programming Language :: Python :: 3.10
Classifier: Programming Language :: Python :: 3.11
Classifier: Programming Language :: Python :: 3.12
Classifier: License :: OSI Approved :: MIT License
Requires-Python: >=3.10
License-File: LICENSE
Requires-Dist: astropy (>=4.3.1)
Requires-Dist: skyfield
Requires-Dist: sgp4
Requires-Dist: spacetrack
Requires-Dist: numpy
Requires-Dist: scipy
Requires-Dist: loess
Requires-Dist: wget
Requires-Dist: pandas
Requires-Dist: colorama
